[{"date":"2022-11-05","meanTemperature":11.02,"medianTemperature":11.02,"stationName":"Zistersdorf","stationId":"meteoblue-zistersdorf"},{"date":"2022-11-06","meanTemperature":10.37,"medianTemperature":10.37,"stationName":"Zistersdorf","stationId":"meteoblue-zistersdorf"},{"date":"2022-11-07","meanTemperature":13.51,"medianTemperature":13.51,"stationName":"Zistersdorf","stationId":"meteoblue-zistersdorf"},{"date":"2022-11-08","meanTemperature":11.01,"medianTemperature":11.01,"stationName":"Zistersdorf","stationId":"meteoblue-zistersdorf"},{"date":"2022-11-09","meanTemperature":9.54,"medianTemperature":9.54,"stationName":"Zistersdorf","stationId":"meteoblue-zistersdorf"},{"date":"2022-11-10","meanTemperature":11.14,"medianTemperature":11.14,"stationName":"Zistersdorf","stationId":"meteoblue-zistersdorf"},{"date":"2022-11-11","meanTemperature":11.18,"medianTemperature":11.18,"stationName":"Zistersdorf","stationId":"meteoblue-zistersdorf"},{"date":"2022-11-12","meanTemperature":10.76,"medianTemperature":10.76,"stationName":"Zistersdorf","stationId":"meteoblue-zistersdorf"}]