[{"date":"2024-03-03","meanTemperature":12.88,"medianTemperature":12.88,"stationName":"Zistersdorf","stationId":"openweathermap-zistersdorf"},{"date":"2024-03-04","meanTemperature":12.71,"medianTemperature":12.71,"stationName":"Zistersdorf","stationId":"openweathermap-zistersdorf"},{"date":"2024-03-05","meanTemperature":11.85,"medianTemperature":11.85,"stationName":"Zistersdorf","stationId":"openweathermap-zistersdorf"},{"date":"2024-03-06","meanTemperature":9.96,"medianTemperature":9.96,"stationName":"Zistersdorf","stationId":"openweathermap-zistersdorf"},{"date":"2024-03-07","meanTemperature":9.86,"medianTemperature":9.86,"stationName":"Zistersdorf","stationId":"openweathermap-zistersdorf"},{"date":"2024-03-08","meanTemperature":6.95,"medianTemperature":6.95,"stationName":"Zistersdorf","stationId":"openweathermap-zistersdorf"},{"date":"2024-03-09","meanTemperature":5.36,"medianTemperature":5.36,"stationName":"Zistersdorf","stationId":"openweathermap-zistersdorf"},{"date":"2024-03-10","meanTemperature":5.72,"medianTemperature":5.72,"stationName":"Zistersdorf","stationId":"openweathermap-zistersdorf"}]