[{"date":"2022-01-07","meanTemperature":0.84,"medianTemperature":0.84,"stationName":"Zistersdorf","stationId":"meteoblue-zistersdorf"},{"date":"2022-01-08","meanTemperature":-0.39,"medianTemperature":-0.39,"stationName":"Zistersdorf","stationId":"meteoblue-zistersdorf"},{"date":"2022-01-09","meanTemperature":-0.01,"medianTemperature":-0.01,"stationName":"Zistersdorf","stationId":"meteoblue-zistersdorf"},{"date":"2022-01-10","meanTemperature":2.61,"medianTemperature":2.61,"stationName":"Zistersdorf","stationId":"meteoblue-zistersdorf"},{"date":"2022-01-11","meanTemperature":1.52,"medianTemperature":1.52,"stationName":"Zistersdorf","stationId":"meteoblue-zistersdorf"},{"date":"2022-01-12","meanTemperature":-1.19,"medianTemperature":-1.19,"stationName":"Zistersdorf","stationId":"meteoblue-zistersdorf"},{"date":"2022-01-13","meanTemperature":-2.64,"medianTemperature":-2.64,"stationName":"Zistersdorf","stationId":"meteoblue-zistersdorf"},{"date":"2022-01-14","meanTemperature":-1.43,"medianTemperature":-1.43,"stationName":"Zistersdorf","stationId":"meteoblue-zistersdorf"}]