[{"date":"2022-01-30","meanTemperature":6.65,"medianTemperature":6.65,"stationName":"Zistersdorf","stationId":"meteoblue-zistersdorf"},{"date":"2022-01-31","meanTemperature":3.75,"medianTemperature":3.75,"stationName":"Zistersdorf","stationId":"meteoblue-zistersdorf"},{"date":"2022-02-01","meanTemperature":3.73,"medianTemperature":3.73,"stationName":"Zistersdorf","stationId":"meteoblue-zistersdorf"},{"date":"2022-02-02","meanTemperature":5.92,"medianTemperature":5.92,"stationName":"Zistersdorf","stationId":"meteoblue-zistersdorf"},{"date":"2022-02-03","meanTemperature":5.48,"medianTemperature":5.48,"stationName":"Zistersdorf","stationId":"meteoblue-zistersdorf"},{"date":"2022-02-04","meanTemperature":4.64,"medianTemperature":4.64,"stationName":"Zistersdorf","stationId":"meteoblue-zistersdorf"},{"date":"2022-02-05","meanTemperature":6.16,"medianTemperature":6.16,"stationName":"Zistersdorf","stationId":"meteoblue-zistersdorf"},{"date":"2022-02-06","meanTemperature":6.8,"medianTemperature":6.8,"stationName":"Zistersdorf","stationId":"meteoblue-zistersdorf"}]