[{"date":"2023-10-26","meanTemperature":17.12,"medianTemperature":17.12,"stationName":"Zistersdorf","stationId":"openweathermap-zistersdorf"},{"date":"2023-10-27","meanTemperature":10.53,"medianTemperature":10.53,"stationName":"Zistersdorf","stationId":"openweathermap-zistersdorf"},{"date":"2023-10-28","meanTemperature":13.69,"medianTemperature":13.69,"stationName":"Zistersdorf","stationId":"openweathermap-zistersdorf"},{"date":"2023-10-29","meanTemperature":11.93,"medianTemperature":11.93,"stationName":"Zistersdorf","stationId":"openweathermap-zistersdorf"},{"date":"2023-10-30","meanTemperature":14.25,"medianTemperature":14.25,"stationName":"Zistersdorf","stationId":"openweathermap-zistersdorf"},{"date":"2023-10-31","meanTemperature":17.96,"medianTemperature":17.96,"stationName":"Zistersdorf","stationId":"openweathermap-zistersdorf"},{"date":"2023-11-01","meanTemperature":13.53,"medianTemperature":13.53,"stationName":"Zistersdorf","stationId":"openweathermap-zistersdorf"},{"date":"2023-11-02","meanTemperature":10.63,"medianTemperature":10.63,"stationName":"Zistersdorf","stationId":"openweathermap-zistersdorf"}]