[{"date":"2023-02-08","meanTemperature":0.25,"medianTemperature":0.25,"stationName":"Zistersdorf","stationId":"openweathermap-zistersdorf"},{"date":"2023-02-09","meanTemperature":1.53,"medianTemperature":1.53,"stationName":"Zistersdorf","stationId":"openweathermap-zistersdorf"},{"date":"2023-02-10","meanTemperature":3.29,"medianTemperature":3.29,"stationName":"Zistersdorf","stationId":"openweathermap-zistersdorf"},{"date":"2023-02-11","meanTemperature":4.97,"medianTemperature":4.97,"stationName":"Zistersdorf","stationId":"openweathermap-zistersdorf"},{"date":"2023-02-12","meanTemperature":4.6,"medianTemperature":4.6,"stationName":"Zistersdorf","stationId":"openweathermap-zistersdorf"},{"date":"2023-02-13","meanTemperature":5.12,"medianTemperature":5.12,"stationName":"Zistersdorf","stationId":"openweathermap-zistersdorf"},{"date":"2023-02-14","meanTemperature":8.48,"medianTemperature":8.48,"stationName":"Zistersdorf","stationId":"openweathermap-zistersdorf"},{"date":"2023-02-15","meanTemperature":7.67,"medianTemperature":7.67,"stationName":"Zistersdorf","stationId":"openweathermap-zistersdorf"}]